release_tools/__init__.py
release_tools/_version.py
release_tools/delete_from_release.py
release_tools/download_from_release.py
release_tools/generate_lists.py
release_tools/upload_to_release.py
release_tools/utils.py
gh_release_tools-0.1.14.dist-info/METADATA
gh_release_tools-0.1.14.dist-info/WHEEL
gh_release_tools-0.1.14.dist-info/entry_points.txt
gh_release_tools-0.1.14.dist-info/RECORD
