Metadata-Version: 2.4
Name: gh_release_tools
Version: 0.1.14
Summary: Tools for data wrangling in github releases
Project-URL: homepage, https://github.com/ramSeraph/release_tools
Project-URL: repository, https://github.com/ramSeraph/release_tools.git
Author-email: Sreeram Kandimalla <kandimalla.sreeram@gmail.com>
Requires-Python: >=3.12
